observ/__init__.py
observ/dep.py
observ/dict_proxy.py
observ/init.py
observ/list_proxy.py
observ/object_utils.py
observ/proxy.py
observ/proxy_db.py
observ/scheduler.py
observ/set_proxy.py
observ/traps.py
observ/watcher.py
observ-0.17.1.dist-info/METADATA
observ-0.17.1.dist-info/WHEEL
observ-0.17.1.dist-info/licenses/LICENSE
observ-0.17.1.dist-info/RECORD
