Metadata-Version: 2.4
Name: observ
Version: 0.17.1
Summary: Reactive state management for Python
Project-URL: Homepage, https://github.com/fork-tongue/observ
Author-email: Korijn van Golen <korijn@gmail.com>, Berend Klein Haneveld <berendkleinhaneveld@gmail.com>
License-Expression: MIT
License-File: LICENSE
Requires-Python: >=3.9
